{"cameraMode":{"drawMode":0,"name":"Shaded","section":"Shading Mode"},"sceneLighting":true,"audioPlay":false,"sceneViewState":{"m_AlwaysRefresh":false,"showFog":true,"showSkybox":true,"showFlares":true,"showImageEffects":true,"showParticleSystems":true,"showVisualEffectGraphs":true,"m_FxEnabled":true},"in2DMode":false,"pivot":{"x":559.6123046875,"y":240.46096801757813,"z":1376.1171875},"rotation":{"x":0.025495098903775216,"y":0.005996074993163347,"z":-0.00019814529514405876,"w":0.9996184706687927},"size":925.3565673828125,"orthographic":false}